aigpy/LockHelper.py
aigpy/__init__.py
aigpy/cmdHelper.py
aigpy/convertHelper.py
aigpy/dictHelper.py
aigpy/downloadHelper.py
aigpy/ffmpegHelper.py
aigpy/fileHelper.py
aigpy/githubHelper.py
aigpy/m3u8Helper.py
aigpy/memoryHelper.py
aigpy/modelHelper.py
aigpy/musicHelp.py
aigpy/netHelper.py
aigpy/pathHelper.py
aigpy/pipHelper.py
aigpy/progressHelper.py
aigpy/stringHelper.py
aigpy/systemHelper.py
aigpy/tagHelper.py
aigpy/threadHelper.py
aigpy/timeHelp.py
aigpy-2022.7.8.1.dist-info/LICENSE
aigpy-2022.7.8.1.dist-info/METADATA
aigpy-2022.7.8.1.dist-info/WHEEL
aigpy-2022.7.8.1.dist-info/top_level.txt
aigpy-2022.7.8.1.dist-info/RECORD
