Metadata-Version: 1.0
Name: aigpy
Version: 2022.7.8.1
Summary: Python Common Tool
Home-page: UNKNOWN
Author: Yaronzz
Author-email: yaronhuang@foxmail.com
License: MIT Licence
Platform: any
